topology/__init__.py
topology/__main__.py
topology/args.py
topology/interact.py
topology/logging.py
topology/manager.py
topology/graph/__init__.py
topology/graph/exceptions.py
topology/graph/graph.py
topology/graph/link.py
topology/graph/node.py
topology/graph/port.py
topology/libraries/__init__.py
topology/libraries/common.py
topology/libraries/manager.py
topology/libraries/utils.py
topology/platforms/__init__.py
topology/platforms/debug.py
topology/platforms/manager.py
topology/platforms/node.py
topology/platforms/platform.py
topology/platforms/service.py
topology/platforms/shell.py
topology/platforms/utils.py
topology/pytest/__init__.py
topology/pytest/plugin.py
topology-1.20.5.dist-info/licenses/LICENSE
topology-1.20.5.dist-info/METADATA
topology-1.20.5.dist-info/WHEEL
topology-1.20.5.dist-info/entry_points.txt
topology-1.20.5.dist-info/top_level.txt
topology-1.20.5.dist-info/RECORD
