Metadata-Version: 2.4
Name: topology
Version: 1.20.5
Summary: Topology is a framework for building and testing network topologies, with support for pytest.
Home-page: http://topology.rtfd.org/
Author: Hewlett Packard Enterprise Development LP
Author-email: hpe-networking@lists.hp.com
Keywords: topology
Classifier: Development Status :: 5 - Production/Stable
Classifier: Intended Audience :: Developers
Classifier: License :: OSI Approved :: Apache Software License
Classifier: Natural Language :: English
Classifier: Operating System :: POSIX :: Linux
Classifier: Programming Language :: Python :: 3
Classifier: Programming Language :: Python :: 3.6
Classifier: Programming Language :: Python :: 3.7
Classifier: Programming Language :: Python :: 3.8
Classifier: Programming Language :: Python :: 3.9
Classifier: Programming Language :: Python :: 3.10
Requires-Python: >=3.6
License-File: LICENSE
Requires-Dist: importlib-metadata; python_version < "3.8"
Requires-Dist: six
Requires-Dist: pexpect>=4.6
Requires-Dist: pyparsing
Requires-Dist: pynml
Requires-Dist: pyszn>=1.4.0
Requires-Dist: typing_extensions
Requires-Dist: pprintpp
Requires-Dist: deepdiff
Dynamic: author
Dynamic: author-email
Dynamic: classifier
Dynamic: description
Dynamic: description-content-type
Dynamic: home-page
Dynamic: keywords
Dynamic: license-file
Dynamic: requires-dist
Dynamic: requires-python
Dynamic: summary
